rashi_discord/__init__.py
rashi_discord/index.py
rashi_discord/interfaces.py
rashi_discord-0.1.0.dist-info/METADATA
rashi_discord-0.1.0.dist-info/WHEEL
rashi_discord-0.1.0.dist-info/top_level.txt
rashi_discord-0.1.0.dist-info/RECORD
