Metadata-Version: 2.4
Name: rashi-discord
Version: 0.1.0
Summary: Custom Discord bot library rewritten from TS to Python
Author: Malzahir
Requires-Dist: discord.py>=2.3.0
Requires-Dist: pymongo>=4.6.0
Requires-Dist: aiohttp>=3.9.0
